setup.py
bin/vc
vcosc/__init__.py
vcosc/gpio.py
vcosc/osc.py
vcosc.egg-info/PKG-INFO
vcosc.egg-info/SOURCES.txt
vcosc.egg-info/dependency_links.txt
vcosc.egg-info/not-zip-safe
vcosc.egg-info/requires.txt
vcosc.egg-info/top_level.txt