Metadata-Version: 1.0
Name: vcosc
Version: 0.0.1
Summary: A set of tools to provide message passing between a custom DAC and OSC
Home-page: http://hecanjog.com
Author: He Can Jog
Author-email: erik@hecanjog.com
License: Public Domain
Platform: UNKNOWN
